cambak/__init__.py
cambak/__main__.py
cambak/backup.py
cambak/cameras/Sony.py
cambak/cameras/__init__.py
cambak/scanner.py
cambak-0.1.1.dist-info/entry_points.txt
cambak-0.1.1.dist-info/WHEEL
cambak-0.1.1.dist-info/METADATA
cambak-0.1.1.dist-info/RECORD
