Metadata-Version: 2.1
Name: cambak
Version: 0.1.1
Summary: Simple tool for automating the derushing process of your cameras
Home-page: https://github.com/Themimitoof/cambak.git
License: MIT
Author: Michael Vieira
Author-email: github@mvieira.fr
Requires-Python: >=3.6
Classifier: License :: OSI Approved :: MIT License
Classifier: Programming Language :: Python :: 3
Classifier: Programming Language :: Python :: 3.6
Classifier: Programming Language :: Python :: 3.7
Classifier: Programming Language :: Python :: 3.8
Project-URL: Repository, https://github.com/Themimitoof/cambak.git
